rst2sile-0.2.3.data/scripts/rst2pdf
rst2sile-0.2.3.data/scripts/rst2sile
rst2sile-0.2.3.dist-info/DESCRIPTION.rst
rst2sile-0.2.3.dist-info/METADATA
rst2sile-0.2.3.dist-info/RECORD
rst2sile-0.2.3.dist-info/WHEEL
rst2sile-0.2.3.dist-info/metadata.json
rst2sile-0.2.3.dist-info/top_level.txt
sile/__init__.py
sile/styles.css
sile/packages/bullets.lua
sile/packages/footnotes.lua
sile/packages/pdf.lua
sile/packages/url.lua
