Metadata-Version: 2.0
Name: rst2sile
Version: 0.2.3
Summary: UNKNOWN
Home-page: UNKNOWN
Author: UNKNOWN
Author-email: UNKNOWN
License: UNKNOWN
Platform: UNKNOWN
Requires-Dist: tinycss
Requires-Dist: docutils
Requires-Dist: roman
